autoset_pwd/__init__.py
autoset_pwd/py.typed
autoset_pwd-0.1.dist-info/METADATA
autoset_pwd-0.1.dist-info/WHEEL
autoset_pwd-0.1.dist-info/entry_points.txt
autoset_pwd-0.1.dist-info/RECORD
