Metadata-Version: 2.1
Name: autoset_pwd
Version: 0.1
Summary: Automatically set $PWD as an environment-variable.
Home-page: https://github.com/libranet/autoset-pwd
License: MIT
Keywords: entrypoints,sitecustomize,pwd
Author: Wouter Vanden Hove
Author-email: wouter@libranet.eu
Maintainer: Wouter Vanden Hove
Maintainer-email: wouter@libranet.eu
Requires-Python: >=3.8.0
Classifier: Development Status :: 4 - Beta
Classifier: Environment :: Console
Classifier: Intended Audience :: Developers
Classifier: License :: OSI Approved :: MIT License
Classifier: Natural Language :: English
Classifier: Operating System :: POSIX :: Linux
Classifier: Programming Language :: Python :: 3
Classifier: Programming Language :: Python :: 3.8
Classifier: Programming Language :: Python :: 3.9
Classifier: Programming Language :: Python :: 3.10
Classifier: Programming Language :: Python :: 3.11
Classifier: Programming Language :: Python :: Implementation :: CPython
Classifier: Programming Language :: Python :: Implementation :: PyPy
Classifier: Topic :: Software Development
Classifier: Topic :: Software Development :: Libraries
Classifier: Typing :: Typed
Requires-Dist: sitecustomize-entrypoints (>=1.1)
Project-URL: Changelog, https://github.com/libranet/autoset-pwd/blob/main/docs/changes.md
Project-URL: Documentation, https://autoset-pwd.readthedocs.io
Project-URL: Issues, https://github.com/libranet/autoset-pwd/issues
Project-URL: Repository, https://github.com/libranet/autoset-pwd
Project-URL: Releases, https://github.com/libranet/autoset-pwd/releases
